{
  "run_id": "run-1773902688288-kqq1hcw",
  "timestamp_utc": "2026-03-19T06:44:48.288Z",
  "trunk_id": "5.0",
  "session_ref": "enc-stub-005",
  "pass": true,
  "results": [
    {
      "check": "no_invented_codes",
      "passed": true
    },
    {
      "check": "no_invented_guidelines",
      "passed": true
    },
    {
      "check": "no_invented_operations",
      "passed": true
    },
    {
      "check": "no_repo_invention",
      "passed": true
    },
    {
      "check": "hard_stop_enforcement",
      "passed": true
    }
  ],
  "missing_receipts": []
}